varplus/__init__.py
varplus/varbase.py
varplus/varrules.py
varplus-0.1.2.dist-info/METADATA
varplus-0.1.2.dist-info/WHEEL
varplus-0.1.2.dist-info/top_level.txt
varplus-0.1.2.dist-info/RECORD
